mac.sv
module
    mac (
parameter ARRAY_SIZE = 8,  //array size nxn mac units
parameter DATA_WIDTH = 8,   // int8 input width
parameter ACCUM_WIDTH = 21
)(
        input logic clk,
        input  logic rst_n,    // _n: negative logic
        input logic signed [(DATA_WIDTH-1):0] a_in,     // int8
        input logic signed [(DATA_WIDTH-1):0] b_in,
        input logic valid,
        input logic clear,
        output logic  signed [(DATA_WIDTH-1):0] a_out,
        output logic  signed [(DATA_WIDTH-1):0]b_out,
        output logic  signed [ACCUM_WIDTH-1:0] acc
    );
    
    
  always_ff @(posedge clk or negedge rst_n)
  begin
    if(!rst_n)
    begin
      a_out<= 8'h00;
      b_out<= 8'h00;
      acc<= 0;
    end
    else
    begin
      a_out<=a_in;
      b_out<=b_in;
      if(clear)
      begin
        acc<=0;
      end
      else if (valid) 
      begin
      acc<=acc +(a_in*b_in);  
      end
    end
  end

endmodule

tb_mac.v
`timescale 1ps/1ps

module tb_mac;

reg clk;
reg rst_n;
reg signed [7:0] a_in,b_in;
wire signed [20:0]acc ;
reg valid,clear;
wire signed[7:0] a_out, b_out;
 mac dut (
        .clk(clk),
        .rst_n(rst_n),
        .a_in(a_in),
        .b_in(b_in),
        .valid(valid),
        .clear(clear),
        .a_out(a_out),
        .b_out(b_out),
        .acc(acc)
    );


initial begin
    $monitor("Time=%0t | a=%0d b=%0d | a_out=%0d b_out=%0d | valid=%b clear=%b | acc=%0d",
             $time, a_in, b_in, a_out, b_out, valid, clear, acc);
end

initial begin
    clk= 0;
    forever begin
        #5 clk= ~clk;
    end
end

   initial begin
        $dumpfile("mac.vcd");
        $dumpvars(0, tb_mac);
    end

    //--------------------------------------------------
    // Test sequence
    //--------------------------------------------------
    initial begin

        // Initialize
        rst_n = 0;
        clear = 0;
        valid = 0;
        a_in = 0;
        b_in = 0;

        #12;

        //--------------------------------------------
        // Release reset
        //--------------------------------------------
        rst_n = 1;

        //--------------------------------------------
        // Test 1
        // 3 × 4 = 12
        //--------------------------------------------
        @(posedge clk);
        valid = 1;
        a_in = 3;
        b_in = 4;

        //--------------------------------------------
        // Test 2
        // +2 × 5 = 10
        //--------------------------------------------
        @(posedge clk);
        a_in = 2;
        b_in = 5;

        //--------------------------------------------
        // Test 3
        // valid = 0
        //--------------------------------------------
        @(posedge clk);
        valid = 0;
        a_in = 7;
        b_in = 7;

        //--------------------------------------------
        // Test 4
        // Clear accumulator
        //--------------------------------------------
        @(posedge clk);
        clear = 1;

        @(posedge clk);
        clear = 0;

        //--------------------------------------------
        // Test 5
        // -2 × 6 = -12
        //--------------------------------------------
        @(posedge clk);
        valid = 1;
        a_in = -2;
        b_in = 6;

        //--------------------------------------------
        // Finish
        //--------------------------------------------
        @(posedge clk);
        $finish;

    end

endmodule

simulations/mac.vcd
$date
	Thu Jul  2 01:50:34 2026
$end
$version
	Icarus Verilog
$end
$timescale
	1ps
$end
$scope module tb_mac $end
$var wire 8 ! b_out [7:0] $end
$var wire 21 " acc [20:0] $end
$var wire 8 # a_out [7:0] $end
$var reg 8 $ a_in [7:0] $end
$var reg 8 % b_in [7:0] $end
$var reg 1 & clear $end
$var reg 1 ' clk $end
$var reg 1 ( rst_n $end
$var reg 1 ) valid $end
$scope module dut $end
$var wire 8 * a_in [7:0] $end
$var wire 8 + b_in [7:0] $end
$var wire 1 & clear $end
$var wire 1 ' clk $end
$var wire 1 ( rst_n $end
$var wire 1 ) valid $end
$var reg 8 , a_out [7:0] $end
$var reg 21 - acc [20:0] $end
$var reg 8 . b_out [7:0] $end
$upscope $end
$upscope $end
$enddefinitions $end
$comment Show the parameter values. $end
$dumpall
$end
#0
$dumpvars
b0 .
b0 -
b0 ,
b0 +
b0 *
0)
0(
0'
0&
b0 %
b0 $
b0 #
b0 "
b0 !
$end
#5
1'
#10
0'
#12
1(
#15
b1100 "
b1100 -
b100 !
b100 .
b11 #
b11 ,
b100 %
b100 +
b11 $
b11 *
1)
1'
#20
0'
#25
b10110 "
b10110 -
b101 !
b101 .
b10 #
b10 ,
b101 %
b101 +
b10 $
b10 *
1'
#30
0'
#35
b111 !
b111 .
b111 #
b111 ,
b111 %
b111 +
b111 $
b111 *
0)
1'
#40
0'
#45
b0 "
b0 -
1&
1'
#50
0'
#55
0&
1'
#60
0'
#65
b111111111111111110100 "
b111111111111111110100 -
b110 !
b110 .
b11111110 #
b11111110 ,
b110 %
b110 +
b11111110 $
b11111110 *
1)
1'
#70
0'
#75
b111111111111111101000 "
b111111111111111101000 -
1'
